{
  "language": "en",
  "ignoreWordsList": [
    "AppVeyor",
    "GitHub",
    "PowerShell",
    "SecurityFever",
    "cmdlets",
    "PowerShellGet",
    "cmdlet",
    "powershell",
    "R2",
    "WMF",
    "Spizzi",
    "CurrentUser",
    "AllUsers",
    "auditpol",
    "exe",
    "sudo",
    "ps1",
    "claudiospizzi",
    "PowerShellModuleBase",
    "-Scope",
    "Get-SecurityActivity",
    "Get-SecurityAuditPolicy",
    "Get-SecurityAuditPolicySetting",
    "PSCredential",
    "Get-VaultEntry",
    "Get-VaultEntryCredential",
    "Get-VaultEntrySecureString",
    "New-VaultEntry",
    "Update-VaultEntry",
    "Remove-VaultEntry",
    "Throw",
    "-Quiet"
  ],
  "mistakeTypeToStatus": {
    "Passive voice": "Hint",
    "Spelling": "Error",
    "Complex Expression": "Disable",
    "Hidden Verbs": "Information",
    "Hyphen Required": "Disable",
    "Redundant Expression": "Disable",
    "Did you mean...": "Disable",
    "Repeated Word": "Warning",
    "Missing apostrophe": "Warning",
    "Cliches": "Disable",
    "Missing Word": "Disable",
    "Make I uppercase": "Warning"
  },
  "languageIDs": [
    "markdown"
  ],
  "ignoreRegExp": [
    "/\\(.*\\.(jpg|jpeg|png|md|gif|JPG|JPEG|PNG|MD|GIF)\\)/g",
    "/((http|https|ftp|git)\\S*)/g"
  ]
}